goip32/__init__.py
goip32/__main__.py
goip32/api.py
goip32/cli.py
goip32/exceptions.py
goip32-0.0.1.dist-info/licenses/LICENSE
goip32-0.0.1.dist-info/METADATA
goip32-0.0.1.dist-info/WHEEL
goip32-0.0.1.dist-info/entry_points.txt
goip32-0.0.1.dist-info/top_level.txt
goip32-0.0.1.dist-info/RECORD
