Metadata-Version: 2.4
Name: goip32
Version: 0.0.1
Summary: A simple api for goip32
Author-email: Dominik Stanisław Suchora <hexderm@gmail.com>
License: GPLv3
Project-URL: Homepage, https://github.com/TUVIMEN/goip32
Keywords: api,goip,gsm,goip32
Classifier: Development Status :: 4 - Beta
Classifier: License :: OSI Approved :: GNU General Public License v3 (GPLv3)
Classifier: Operating System :: OS Independent
Classifier: Programming Language :: Python :: 3
Classifier: Programming Language :: Python :: 3.8
Classifier: Programming Language :: Python :: 3.9
Classifier: Programming Language :: Python :: 3.10
Classifier: Programming Language :: Python :: 3.11
Classifier: Programming Language :: Python :: 3.12
Classifier: Programming Language :: Python :: 3.13
Classifier: Programming Language :: Python :: 3 :: Only
Requires-Python: >=3.8
License-File: LICENSE
Requires-Dist: requests
Requires-Dist: reliq
Requires-Dist: treerequests
Dynamic: license-file
